zigpy_zigate/__init__.py
zigpy_zigate/api.py
zigpy_zigate/common.py
zigpy_zigate/types.py
zigpy_zigate/uart.py
zigpy_zigate/tools/__init__.py
zigpy_zigate/tools/cli.py
zigpy_zigate/tools/firmware.py
zigpy_zigate/tools/flasher.py
zigpy_zigate/zigbee/__init__.py
zigpy_zigate/zigbee/application.py
zigpy_zigate-0.13.3.dist-info/licenses/COPYING
zigpy_zigate-0.13.3.dist-info/licenses/LICENSE
zigpy_zigate-0.13.3.dist-info/METADATA
zigpy_zigate-0.13.3.dist-info/WHEEL
zigpy_zigate-0.13.3.dist-info/top_level.txt
zigpy_zigate-0.13.3.dist-info/RECORD
