Metadata-Version: 2.4
Name: zigpy-zigate
Version: 0.13.3
Summary: A library which communicates with ZiGate radios for zigpy
Author-email: Sébastien RAMAGE <sebatien.ramage@gmail.com>
License: GPL-3.0
Project-URL: repository, https://github.com/zigpy/zigpy-zigate
Requires-Python: >=3.8
License-File: LICENSE
License-File: COPYING
Requires-Dist: voluptuous
Requires-Dist: zigpy>=0.70.0
Requires-Dist: pyusb>=1.1.0
Requires-Dist: gpiozero
Requires-Dist: async-timeout; python_version < "3.11"
Provides-Extra: testing
Requires-Dist: pytest>=7.1.2; extra == "testing"
Requires-Dist: pytest-asyncio>=0.19.0; extra == "testing"
Requires-Dist: pytest-timeout>=2.1.0; extra == "testing"
Requires-Dist: pytest-mock>=3.8.2; extra == "testing"
Requires-Dist: pytest-cov>=3.0.0; extra == "testing"
Dynamic: license-file
